{
  "project_info": {
    "project_number": "720734785507",
    "firebase_url": "https://moelayadmin-e8107.firebaseio.com",
    "project_id": "moelayadmin-e8107",
    "storage_bucket": "moelayadmin-e8107.appspot.com"
  },
  "client": [
    {
      "client_info": {
        "mobilesdk_app_id": "1:720734785507:android:937444aa1961480c621ad6",
        "android_client_info": {
          "package_name": "com.sawkyawhtin.mmovies"
        }
      },
      "oauth_client": [
        {
          "client_id": "720734785507-7c52resqab6f3nskudp1r39uj27kupun.apps.googleusercontent.com",
          "client_type": 1,
          "android_info": {
            "package_name": "com.sawkyawhtin.mmovies",
            "certificate_hash": "8068651d190f26ec005aa633ac9d375def864f1f"
          }
        },
        {
          "client_id": "720734785507-999113mmotm71t2crupk2hlrmqragv6q.apps.googleusercontent.com",
          "client_type": 3
        }
      ],
      "api_key": [
        {
          "current_key": "AIzaSyCTFKOjYHUo2xwngdfQTkpaRm7ZGeXM2hE"
        }
      ],
      "services": {
        "appinvite_service": {
          "other_platform_oauth_client": [
            {
              "client_id": "720734785507-999113mmotm71t2crupk2hlrmqragv6q.apps.googleusercontent.com",
              "client_type": 3
            }
          ]
        }
      }
    },
    {
      "client_info": {
        "mobilesdk_app_id": "1:720734785507:android:74ed5c6217756d92621ad6",
        "android_client_info": {
          "package_name": "com.sawkyawhtin.moelayadmin"
        }
      },
      "oauth_client": [
        {
          "client_id": "720734785507-i84cafes1eghu5fosacvfpuol3djom5o.apps.googleusercontent.com",
          "client_type": 1,
          "android_info": {
            "package_name": "com.sawkyawhtin.moelayadmin",
            "certificate_hash": "8068651d190f26ec005aa633ac9d375def864f1f"
          }
        },
        {
          "client_id": "720734785507-999113mmotm71t2crupk2hlrmqragv6q.apps.googleusercontent.com",
          "client_type": 3
        }
      ],
      "api_key": [
        {
          "current_key": "AIzaSyCTFKOjYHUo2xwngdfQTkpaRm7ZGeXM2hE"
        }
      ],
      "services": {
        "appinvite_service": {
          "other_platform_oauth_client": [
            {
              "client_id": "720734785507-999113mmotm71t2crupk2hlrmqragv6q.apps.googleusercontent.com",
              "client_type": 3
            }
          ]
        }
      }
    }
  ],
  "configuration_version": "1"
}